[
    { "title": "유리구두 (From fromis_9 Pre-Debut)","singer": ["all"], "mood": [""], "time": [""], "youtubeId": "n2TtQYuFfWw", "howabout": {} },
    { "title": "나에게로 오는 길 (Intro)","singer": ["all"], "mood": [""], "time": [""], "youtubeId": "Co9H3xLBv6M", "howabout": {} },
    { "title": "To Heart","singer": ["all"], "mood": [""], "time": [""], "youtubeId": "iFUHS1Ei7qw", "howabout": {} },
    { "title": "환상속의 그대","singer": ["all"], "mood": [""], "time": [""], "youtubeId": "FQw-egUublA", "howabout": {} },
    { "title": "피노키오","singer": ["all"], "mood": [""], "time": [""], "youtubeId": "4dlYexMXJwk", "howabout": {} },
    { "title": "Be With You","singer": ["all"], "mood": [""], "time": [""], "youtubeId": "TLvtoIy4Q30", "howabout": {} },
    { "title": "다가가고 싶어","singer": ["all"], "mood": [""], "time": [""], "youtubeId": "zV4J4FuXZ", "howabout": {} },
    { "title": "너를 따라, 너에게","singer": ["all"], "mood": [""], "time": [""], "youtubeId": "uK3aeZIQKNA", "howabout": {} },
    { "title": "두근두근 (DKDK)","singer": ["all"], "mood": [""], "time": [""], "youtubeId": "B3KuJqe3Epg", "howabout": {} },
    { "title": "22세기 소녀","singer": ["all"], "mood": [""], "time": [""], "youtubeId": "47kyZZSm3D4", "howabout": {} },
    { "title": "CLOVER","singer": ["all"], "mood": [""], "time": [""], "youtubeId": "6TWeJ9A8LHg", "howabout": {} },
    { "title": "FIRST LOVE","singer": ["all"], "mood": [""], "time": [""], "youtubeId": "aqR9wb1ihyE", "howabout": {} },
    { "title": "LOVE BOMB","singer": ["all"], "mood": [""], "time": [""], "youtubeId": "d4tBlQ5yTwY", "howabout": {} },
    { "title": "DANCING QUEEN","singer": ["all"], "mood": [""], "time": [""], "youtubeId": "UV3sSj9geSs", "howabout": {} },
    { "title": "물들어","singer": ["all"], "mood": [""], "time": [""], "youtubeId": "0ZsnEh8TWGE", "howabout": {} },
    { "title": "FUN!","singer": ["all"], "mood": [""], "time": [""], "youtubeId": "zsRyyLtcXho", "howabout": {} },
    { "title": "LOVE RUMPUMPUM","singer": ["all"], "mood": [""], "time": [""], "youtubeId": "TEwC0zt721w", "howabout": {} },
    { "title": "FLY HIGH","singer": ["all"], "mood": [""], "time": [""], "youtubeId": "DeC7KrvKNO4", "howabout": {} },
    { "title": "Feel Good (SECRET CODE)","singer": ["all"], "mood": [""], "time": [""], "youtubeId": "jLmJhjCzOTw", "howabout": {} },
    { "title": "Weather","singer": ["all"], "mood": [""], "time": [""], "youtubeId": "r7ucU5ONXn8", "howabout": {} },
    { "title": "별의 밤","singer": ["all"], "mood": [""], "time": [""], "youtubeId": "vA5oAt3oG14", "howabout": {} },
    { "title": "Somebody to Love","singer": ["all"], "mood": [""], "time": [""], "youtubeId": "j9Oh19mZG5k", "howabout": {} },
    { "title": "물고기","singer": ["all"], "mood": [""], "time": [""], "youtubeId": "Ipi_kedxeN8", "howabout": {} },
    { "title": "Airplane Mode","singer": ["all"], "mood": [""], "time": [""], "youtubeId": "p7h4R3v79BI", "howabout": {} },
    { "title": "WE GO","singer": ["all"], "mood": [""], "time": [""], "youtubeId": "HM6UpQZvbhY", "howabout": {"likeyoubetter": [9]} },
    { "title": "Promise","singer": ["all"], "mood": [""], "time": [""], "youtubeId": "OpJk8_4Vbi0", "howabout": {} },
    { "title": "Talk & Talk","singer": ["all"], "mood": [""], "time": [""], "youtubeId": "BjmmvBMXbSU", "howabout": {} },
    { "title": "별","singer": ["all"], "mood": [""], "time": [""], "youtubeId": "cYD0-OaRAmw", "howabout": {} },
    { "title": "Escape Room","singer": ["all"], "mood": [""], "time": [""], "youtubeId": "BPTcweDPdnU", "howabout": {} },
    { "title": "DM","singer": ["all"], "mood": [""], "time": [""], "youtubeId": "4gXmClk8rKI", "howabout": { "likeyoubetter": [4] } },
    { "title": "Love is Around","singer": ["all"], "mood": [""], "time": [""], "youtubeId": "8VGyWD8Pq9o", "howabout": {} },
    { "title": "Hush Hush","singer": ["all"], "mood": [""], "time": [""], "youtubeId": "0TfGtiD2HXc", "howabout": {} },
    { "title": "0g","singer": ["all"], "mood": [""], "time": [""], "youtubeId": "l2S7HPsWW7Y", "howabout": {} },
    { "title": "Stay Alive","singer": ["all"], "mood": [""], "time": [""], "youtubeId": "Pu0kpKvPPV0", "howabout": {} },
    { "title": "Up And","singer": ["all"], "mood": [""], "time": [""], "youtubeId": "44AIBLEJfmQ", "howabout": {} },
    { "title": "Stay This Way","singer": ["all"], "mood": [""], "time": [""], "youtubeId": "JC6budcACNE", "howabout": {"likeyoubetter": [10]} },
    { "title": "Blind Letter","singer": ["all"], "mood": [""], "time": [""], "youtubeId": "S7xpvOVfclg", "howabout": {} },
    { "title": "Cheese","singer": ["all"], "mood": [""], "time": [""], "youtubeId": "xKI1gdlDzxc", "howabout": {} },
    { "title": "Rewind","singer": ["all"], "mood": [""], "time": [""], "youtubeId": "pujG9jmL9QY", "howabout": {} },
    { "title": "달빛바다","singer": ["all"], "mood": [""], "time": [""], "youtubeId": "peBkYOfFAd4", "howabout": {} },
    { "title": "Love Me Back","singer": ["all"], "mood": [""], "time": [""], "youtubeId": "EE8655GDT9k", "howabout": {} },
    { "title": "Supersonic","singer": ["all"], "mood": [""], "time": [""], "youtubeId": "0LiQp7y8Wwc", "howabout": { "likeyoubetter": [5,14] } },
    { "title": "Beat the Heat","singer": ["all"], "mood": [""], "time": [""], "youtubeId": "jkH89xvz2v8", "howabout": {} },
    { "title": "Take A Chance","singer": ["all"], "mood": [""], "time": [""], "youtubeId": "06_3xYmZUig", "howabout": {} },
    { "title": "from","singer": ["all"], "mood": [""], "time": [""], "youtubeId": "BA5Tz0Z34SE", "howabout": {"likeyoubetter": [19]} },
    { "title": "LIKE YOU BETTER","singer": ["all"], "mood": [""], "time": [""], "youtubeId": "r1QapH1SIAI", "howabout": { "likeyoubetter": [1,6,11,16] } },
    { "title": "REBELUTIONAL", "singer": ["all"],"mood": [""], "time": [""], "youtubeId": "SrW-ILDJxdM", "howabout": { "likeyoubetter": [2] } },
    { "title": "Love=Disaster","singer": ["all"], "mood": [""], "time": [""], "youtubeId": "RD-gN0ykmV1C4", "howabout": { "likeyoubetter": [3] } },
    { "title": "Strawberry Mimosa","singer": ["all"], "mood": [""], "time": [""], "youtubeId": "7M4hrsyS2mA", "howabout": {"likeyoubetter": [7,13]} },
    { "title": "Twisted love","singer": ["all"], "mood": [""], "time": [""], "youtubeId": "-ArKRflpTxM", "howabout": {"likeyoubetter": [8,18]} },
    { "title": "Merry Go Round","singer": ["all"], "mood": [""], "time": [""], "youtubeId": "b_CpQdKpmjQ", "howabout": {"likeyoubetter": [12]} },
    { "title": "Touchdown","singer": ["all"], "mood": [""], "time": [""], "youtubeId": "peoZYyEvY", "howabout": {} },
    { "title": "Attitude","singer": ["all"], "mood": [""], "time": [""], "youtubeId": "aZ_rZxIu-J8", "howabout": {} },
    { "title": "#menow","singer": ["all"], "mood": [""], "time": [""], "youtubeId": "QrYIOjs7K8E", "howabout": {} },
    { "title": "Wishlist","singer": ["all"], "mood": [""], "time": [""], "youtubeId": "cMUcGLwNusU", "howabout": {} },
    { "title": "In the Mirror","singer": ["all"], "mood": [""], "time": [""], "youtubeId": "c_Ku4W2iCY0", "howabout": {} },
    { "title": "Don't Care","singer": ["all"], "mood": [""], "time": [""], "youtubeId": "tLebrTow3-Q", "howabout": {} },
    { "title": "Prom Night","singer": ["all"], "mood": [""], "time": [""], "youtubeId": "wqYg1gz3EBI", "howabout": {} },
    { "title": "Bring It On","singer": ["all"], "mood": [""], "time": [""], "youtubeId": "SfNagEVfftc", "howabout": {} },
    { "title": "What I Want","singer": ["all"], "mood": [""], "time": [""], "youtubeId": "OHF_zI2lZIk", "howabout": {} },
    { "title": "My Night Routine","singer": ["all"], "mood": [""], "time": [""], "youtubeId": "5ERZhs8xGVc", "howabout": {} },
    { "title": "눈맞춤","singer": ["all"], "mood": [""], "time": [""], "youtubeId": "-0VWWvubirY", "howabout": {"likeyoubetter": [15]} },
    { "title": "잠이 안와","singer": ["송하영"], "mood": [""], "time": [""], "youtubeId": "5uA8DlSJuo0", "howabout": {"likeyoubetter": [17]} },
    { "title": "언제나 난 고양이","singer": ["송하영"], "mood": [""], "time": [""], "youtubeId": "Um4SRLl1GII", "howabout": {} },
    { "title": "봄처럼 다가와","singer": ["송하영", "이나경"], "mood": [""], "time": [""], "youtubeId": "xGeUI2WDO4A", "howabout": {} },
    { "title": "Stay together all day","singer": ["송하영"], "mood": [""], "time": [""], "youtubeId": "EZFBFiD7o", "howabout": {} },
    { "title": "그래도 나 사랑하지","singer": ["송하영"], "mood": [""], "time": [""], "youtubeId": "Qq8Cd65rrqo", "howabout": {} },
    { "title": "너는 나 나는 너 (말하고 싶은 비밀)","singer": ["이서연"], "mood": [""], "time": [""], "youtubeId": "qNeq0aRGk9I", "howabout": {} },
    { "title": "우린 마지막 봄인가 봐","singer": ["이서연"], "mood": [""], "time": [""], "youtubeId": "PmFc65MzfGY", "howabout": {} },
    { "title": "의리소녀 (feat.이서연)","singer": ["이서연"], "mood": [""], "time": [""], "youtubeId": "LEIXB2mbL30", "howabout": {} },
    { "title": "We Are The One","singer": ["박지원"], "mood": [""], "time": [""], "youtubeId": "xZJ5f_LrSpI", "howabout": {} },
    { "title": "네게 말해 (이 여름밤)","singer": ["박지원"], "mood": [""], "time": [""], "youtubeId": "a6Ll_1u-rq4", "howabout": {} },
    { "title": "내 곁을 떠나지 말아요","singer": ["박지원"], "mood": [""], "time": [""], "youtubeId": "m48f2ts_XLk", "howabout": {} },
    { "title": "Love Actually","singer": ["박지원"], "mood": [""], "time": [""], "youtubeId": "oQqNSdMRfIQ", "howabout": {} },
    { "title": "Cloud","singer": ["박지원"], "mood": [""], "time": [""], "youtubeId": "FPI1EgWdZc8", "howabout": {} },
    { "title": "지금부터 시작해","singer": ["박지원"], "mood": [""], "time": [""], "youtubeId": "Wv5PhsAjL8Q", "howabout": {} },
    { "title": "What are we (feat. 박지원)","singer": ["박지원"], "mood": [""], "time": [""], "youtubeId": "oCwgkBrRivI", "howabout": {} },
    { "title": "꿈나라역 1번출구","singer": ["송하영"], "mood": [""], "time": [""], "youtubeId": "6wonCXASIhI", "howabout": {} },
    { "title": "시골 소년의 첫사랑","singer": ["송하영"], "mood": [""], "time": [""], "youtubeId": "XD3wZBklKuY", "howabout": {} },
    { "title": "11월 29일","singer": ["송하영"], "mood": [""], "time": [""], "youtubeId": "Ve_UdhhOasI", "howabout": {} }
]